<annotation>
	<folder>images</folder>
	<filename>1163.jpg</filename>
	<path>1163.jpg</path>
	<source>
		<database>Unknown</database>
	</source>
	<size>
		<width>1920</width>
		<height>1080</height>
		<depth>3</depth>
	</size>
	<segmented>0</segmented>
	<object>
		<name>top</name>
		<pose>Unspecified</pose>
		<truncated>0</truncated>
		<difficult>0</difficult>
		<bndbox>
			<xmin>863</xmin>
			<ymin>252</ymin>
			<xmax>969</xmax>
			<ymax>387</ymax>
		</bndbox>
	</object>
	<object>
		<name>top</name>
		<pose>Unspecified</pose>
		<truncated>0</truncated>
		<difficult>0</difficult>
		<bndbox>
			<xmin>1009</xmin>
			<ymin>320</ymin>
			<xmax>1118</xmax>
			<ymax>468</ymax>
		</bndbox>
	</object>
</annotation>