<annotation>
	<folder>top_image3</folder>
	<filename>944.jpg</filename>
	<path>944.jpg</path>
	<source>
		<database>Unknown</database>
	</source>
	<size>
		<width>1920</width>
		<height>1080</height>
		<depth>3</depth>
	</size>
	<segmented>0</segmented>
	<object>
		<name>top</name>
		<pose>Unspecified</pose>
		<truncated>0</truncated>
		<difficult>0</difficult>
		<bndbox>
			<xmin>496</xmin>
			<ymin>493</ymin>
			<xmax>773</xmax>
			<ymax>768</ymax>
		</bndbox>
	</object>
	<object>
		<name>top</name>
		<pose>Unspecified</pose>
		<truncated>0</truncated>
		<difficult>0</difficult>
		<bndbox>
			<xmin>892</xmin>
			<ymin>396</ymin>
			<xmax>1105</xmax>
			<ymax>638</ymax>
		</bndbox>
	</object>
</annotation>